{
  "Version": "2012-10-17",
  "Statement": [
    {
      "Effect": "Allow",
      "Action": [
        "route53:ChangeResourceRecordSets",
        "route53:ListResourceRecordSets",
        "route53:GetHostedZone",
        "route53:ListHostedZones",
        "route53:CreateHostedZone",
        "route53:DeleteHostedZone",
        "route53:ChangeTagsForResource",
        "route53:ListTagsForResource",
        "route53:GetChange",
        "acm:RequestCertificate",
        "acm:DescribeCertificate",
        "acm:ListCertificates",
        "acm:AddTagsToCertificate",
        "acm:ValidateCertificate",
        "acm:DeleteCertificate"
      ],
      "Resource": "*"
    }
  ]
}
